scribl/__init__.py
scribl/_version.py
scribl/manage_graphdb.py
scribl/parse_scribl.py
scribl/process_graphdb_data.py
scribl/process_zotero.py
scribl/scribl.py
scribl-0.8.4.dist-info/licenses/LICENSE
scribl-0.8.4.dist-info/METADATA
scribl-0.8.4.dist-info/WHEEL
scribl-0.8.4.dist-info/entry_points.txt
scribl-0.8.4.dist-info/top_level.txt
scribl-0.8.4.dist-info/RECORD
