Metadata-Version: 2.4
Name: scribl
Version: 0.8.4
Summary: A system for the semantic capture of relationships in biological literature
Author-email: Amber Biology <info@amberbiology.com>
License: GNU AGPLv3+
Project-URL: Homepage, http://amberbiology.com
Project-URL: Source, https://github.com/amberbiology/scribl/
Project-URL: Tracker, https://github.com/amberbiology/scribl/issues
Project-URL: Changelog, https://github.com/amberbiology/scribl/blob/main/CHANGELOG.md
Keywords: systems biology,network biology,literature database
Classifier: Programming Language :: Python :: 3
Classifier: Intended Audience :: Science/Research
Classifier: Topic :: Scientific/Engineering :: Bio-Informatics
License-File: LICENSE
Requires-Dist: pyparsing<=3.2.5
Requires-Dist: pandas<=2.3.3
Requires-Dist: pyzotero<=1.7.6
Requires-Dist: networkx<=3.6.1
Requires-Dist: matplotlib<=3.10.7
Provides-Extra: test
Requires-Dist: pytest; extra == "test"
Dynamic: license-file
